{
  "kind":"customsearch#search",
  "url":  
  {
    "type":"application/json",
    "template":"https://www.googleapis.com/customsearch/v1?q={searchTerms}&num={count?}&start={startIndex?}&lr={language?}&safe={safe?}&cx={cx?}&sort={sort?}&filter={filter?}&gl={gl?}&cr={cr?}&googlehost={googleHost?}&c2coff={disableCnTwTranslation?}&hq={hq?}&hl={hl?}&siteSearch={siteSearch?}&siteSearchFilter={siteSearchFilter?}&exactTerms={exactTerms?}&excludeTerms={excludeTerms?}&linkSite={linkSite?}&orTerms={orTerms?}&relatedSite={relatedSite?}&dateRestrict={dateRestrict?}&lowRange={lowRange?}&highRange={highRange?}&searchType={searchType}&fileType={fileType?}&rights={rights?}&imgSize={imgSize?}&imgType={imgType?}&imgColorType={imgColorType?}&imgDominantColor={imgDominantColor?}&alt=json"  
  },
  "queries":  
  {
    "previousPage":    
    [
      {
        "title":"Google Custom Search - SNOOP DOGG Before Ego Trippin",
        "totalResults":"2290000",
        "searchTerms":"SNOOP DOGG Before Ego Trippin",
        "count":        10,
        "startIndex":        1,
        "inputEncoding":"utf8",
        "outputEncoding":"utf8",
        "safe":"off",
        "cx":"007439388879951561867:3ragl0fkhpm",
        "searchType":"image",
        "imgSize":"large"      
      }    
    ],
    "request":    
    [
      {
        "title":"Google Custom Search - SNOOP DOGG Before Ego Trippin",
        "totalResults":"2290000",
        "searchTerms":"SNOOP DOGG Before Ego Trippin",
        "count":        10,
        "startIndex":        11,
        "inputEncoding":"utf8",
        "outputEncoding":"utf8",
        "safe":"off",
        "cx":"007439388879951561867:3ragl0fkhpm",
        "searchType":"image",
        "imgSize":"large"      
      }    
    ],
    "nextPage":    
    [
      {
        "title":"Google Custom Search - SNOOP DOGG Before Ego Trippin",
        "totalResults":"2290000",
        "searchTerms":"SNOOP DOGG Before Ego Trippin",
        "count":        10,
        "startIndex":        21,
        "inputEncoding":"utf8",
        "outputEncoding":"utf8",
        "safe":"off",
        "cx":"007439388879951561867:3ragl0fkhpm",
        "searchType":"image",
        "imgSize":"large"      
      }    
    ]  
  },
  "context":  
  {
    "title":"Google"  
  },
  "searchInformation":  
  {
    "searchTime":0.352749,
    "formattedSearchTime":"0.35",
    "totalResults":"2290000",
    "formattedTotalResults":"2,290,000"  
  },
  "items":  
  [
    {
      "kind":"customsearch#result",
      "title":"SNOOP DOGG - Ego Trippin - Amazon.com Music",
      "htmlTitle":"<b>SNOOP DOGG</b> - <b>Ego Trippin</b> - Amazon.com Music",
      "link":"https://images-na.ssl-images-amazon.com/images/I/81hF4ssvQdL._SX466_.jpg",
      "displayLink":"www.amazon.com",
      "snippet":"SNOOP DOGG - Ego Trippin - Amazon.com Music",
      "htmlSnippet":"<b>SNOOP DOGG</b> - <b>Ego Trippin</b> - Amazon.com Music",
      "mime":"image/jpeg",
      "fileFormat":"image/jpeg",
      "image":      
      {
        "contextLink":"https://www.amazon.com/Ego-Trippin-SNOOP-DOGG/dp/B0013FDTYA",
        "height":        466,
        "width":        466,
        "byteSize":        40231,
        "thumbnailLink":"https://encrypted-tbn0.gstatic.com/images?q=tbn:ANd9GcRhU2JaUcWnDo_swcaxBsXJVWlvEtAiRWo8CpzvWhrEyxTB0l-ccL8hGMU6&s",
        "thumbnailHeight":        128,
        "thumbnailWidth":        128      
      }    
    },
    {
      "kind":"customsearch#result",
      "title":"Before Ego Trippin \u2014 Snoop Dogg | Last.fm",
      "htmlTitle":"<b>Before Ego Trippin</b> \u2014 <b>Snoop Dogg</b> | Last.fm",
      "link":"https://lastfm.freetls.fastly.net/i/u/ar0/13a3ef5916054e29ae423dd8eece79a8.jpg",
      "displayLink":"www.last.fm",
      "snippet":"Before Ego Trippin \u2014 Snoop Dogg | Last.fm",
      "htmlSnippet":"<b>Before Ego Trippin</b> \u2014 <b>Snoop Dogg</b> | Last.fm",
      "mime":"image/jpeg",
      "fileFormat":"image/jpeg",
      "image":      
      {
        "contextLink":"https://www.last.fm/music/Snoop+Dogg/Before+Ego+Trippin",
        "height":        500,
        "width":        500,
        "byteSize":        61669,
        "thumbnailLink":"https://encrypted-tbn0.gstatic.com/images?q=tbn:ANd9GcRuMicFWrqH-wZZBlzjMwhDLATdkTG4bqY15AuQ4v1detWxHEF8fN_s4pQ&s",
        "thumbnailHeight":        130,
        "thumbnailWidth":        130      
      }    
    },
    {
      "kind":"customsearch#result",
      "title":"SNOOP DOGG - Ego Trippin - Amazon.com Music",
      "htmlTitle":"<b>SNOOP DOGG</b> - <b>Ego Trippin</b> - Amazon.com Music",
      "link":"https://images-na.ssl-images-amazon.com/images/I/513eixmqtkL.jpg",
      "displayLink":"www.amazon.com",
      "snippet":"SNOOP DOGG - Ego Trippin - Amazon.com Music",
      "htmlSnippet":"<b>SNOOP DOGG</b> - <b>Ego Trippin</b> - Amazon.com Music",
      "mime":"image/jpeg",
      "fileFormat":"image/jpeg",
      "image":      
      {
        "contextLink":"https://www.amazon.com/Ego-Trippin-SNOOP-DOGG/dp/B0013FDTYA",
        "height":        435,
        "width":        500,
        "byteSize":        54376,
        "thumbnailLink":"https://encrypted-tbn0.gstatic.com/images?q=tbn:ANd9GcR7xI3OGAOi1-A21lXcsI5fQLUbmnV2y57Zl4yHUERA3n_WVyF5pFKGJg&s",
        "thumbnailHeight":        113,
        "thumbnailWidth":        130      
      }    
    },
    {
      "kind":"customsearch#result",
      "title":"Snoop Dogg - Ego Trippin (2008, CD) | Discogs",
      "htmlTitle":"<b>Snoop Dogg</b> - <b>Ego Trippin</b> (2008, CD) | Discogs",
      "link":"https://img.discogs.com/HWu4hk3lxfX4ipAdoZxFL5P5_bU=/fit-in/600x586/filters:strip_icc():format(jpeg):mode_rgb():quality(90)/discogs-images/R-11129048-1510403879-2857.jpeg.jpg",
      "displayLink":"www.discogs.com",
      "snippet":"Snoop Dogg - Ego Trippin (2008, CD) | Discogs",
      "htmlSnippet":"<b>Snoop Dogg</b> - <b>Ego Trippin</b> (2008, CD) | Discogs",
      "mime":"image/jpeg",
      "fileFormat":"image/jpeg",
      "image":      
      {
        "contextLink":"https://www.discogs.com/Snoop-Dogg-Ego-Trippin/release/11129048",
        "height":        586,
        "width":        599,
        "byteSize":        133872,
        "thumbnailLink":"https://encrypted-tbn0.gstatic.com/images?q=tbn:ANd9GcR-GiXPpb5otvRTlrp_P-RHz2WSZOxqSMAi8DqHR23jVW48h7Rq2bn0sEYS&s",
        "thumbnailHeight":        132,
        "thumbnailWidth":        135      
      }    
    },
    {
      "kind":"customsearch#result",
      "title":"Snoop Dogg - Ego Trippin JAPAN CD+Bonus Track W/OBI #128-2 for ...",
      "htmlTitle":"<b>Snoop Dogg</b> - <b>Ego Trippin</b> JAPAN CD+Bonus Track W/OBI #128-2 for ...",
      "link":"https://i.ebayimg.com/images/g/S0sAAOSwHxVW7FNz/s-l640.jpg",
      "displayLink":"www.ebay.com",
      "snippet":"Snoop Dogg - Ego Trippin JAPAN CD+Bonus Track W/OBI #128-2 for ...",
      "htmlSnippet":"<b>Snoop Dogg</b> - <b>Ego Trippin</b> JAPAN CD+Bonus Track W/OBI #128-2 for ...",
      "mime":"image/jpeg",
      "fileFormat":"image/jpeg",
      "image":      
      {
        "contextLink":"https://www.ebay.com/c/1502883221",
        "height":        640,
        "width":        640,
        "byteSize":        70789,
        "thumbnailLink":"https://encrypted-tbn0.gstatic.com/images?q=tbn:ANd9GcRNVS0gN2fFi80J0s2LE0A3ydqUfGPKso1z2tf4fO1NcQ64iy3YKaUY6G8&s",
        "thumbnailHeight":        137,
        "thumbnailWidth":        137      
      }    
    },
    {
      "kind":"customsearch#result",
      "title":"Snoop Dogg Ego Trippin' album photo shoot (at Polytechnic High ...",
      "htmlTitle":"<b>Snoop Dogg Ego Trippin</b>&#39; album photo shoot (at Polytechnic High ...",
      "link":"https://i.pinimg.com/564x/d9/5a/3a/d95a3a14ab731e4661ae1f24305bf252.jpg",
      "displayLink":"www.pinterest.com",
      "snippet":"Snoop Dogg Ego Trippin' album photo shoot (at Polytechnic High ...",
      "htmlSnippet":"<b>Snoop Dogg Ego Trippin</b>&#39; album photo shoot (at Polytechnic High ...",
      "mime":"image/jpeg",
      "fileFormat":"image/jpeg",
      "image":      
      {
        "contextLink":"https://www.pinterest.com/pin/156148312068003188/",
        "height":        612,
        "width":        499,
        "byteSize":        49415,
        "thumbnailLink":"https://encrypted-tbn0.gstatic.com/images?q=tbn:ANd9GcSzqkHa7yK4p2_NaUBX-XZWWwKM9cU4QJ1_lztvO91799EPo_5ZQs23U-U&s",
        "thumbnailHeight":        136,
        "thumbnailWidth":        111      
      }    
    },
    {
      "kind":"customsearch#result",
      "title":"Ego Trippin': Amazon.co.uk: Music",
      "htmlTitle":"<b>Ego Trippin</b>&#39;: Amazon.co.uk: Music",
      "link":"https://images-na.ssl-images-amazon.com/images/I/51XLyxJZCHL._AC_SY355_.jpg",
      "displayLink":"www.amazon.co.uk",
      "snippet":"Ego Trippin': Amazon.co.uk: Music",
      "htmlSnippet":"<b>Ego Trippin</b>&#39;: Amazon.co.uk: Music",
      "mime":"image/jpeg",
      "fileFormat":"image/jpeg",
      "image":      
      {
        "contextLink":"https://www.amazon.co.uk/Ego-Trippin-Snoop-Dogg/dp/B0013NFMEM",
        "height":        355,
        "width":        355,
        "byteSize":        30436,
        "thumbnailLink":"https://encrypted-tbn0.gstatic.com/images?q=tbn:ANd9GcRRXgxzK2nbEJ9mDqt2uOB-DepOPbBCs-BjDUYR7FqQXXFEF3VTvwl8&s",
        "thumbnailHeight":        121,
        "thumbnailWidth":        121      
      }    
    },
    {
      "kind":"customsearch#result",
      "title":"Snoop Dogg Photos Photos: Snoop Dogg Signs Copies Of \"Ego Trippin ...",
      "htmlTitle":"<b>Snoop Dogg</b> Photos Photos: <b>Snoop Dogg</b> Signs Copies Of &quot;<b>Ego Trippin</b> ...",
      "link":"https://i.pinimg.com/474x/2c/6e/54/2c6e54fd6409a6aa10fef9a17492ef06.jpg",
      "displayLink":"www.pinterest.com",
      "snippet":"Snoop Dogg Photos Photos: Snoop Dogg Signs Copies Of \"Ego Trippin ...",
      "htmlSnippet":"<b>Snoop Dogg</b> Photos Photos: <b>Snoop Dogg</b> Signs Copies Of &quot;<b>Ego Trippin</b> ...",
      "mime":"image/jpeg",
      "fileFormat":"image/jpeg",
      "image":      
      {
        "contextLink":"https://www.pinterest.com/pin/844706473835013088/",
        "height":        594,
        "width":        452,
        "byteSize":        35662,
        "thumbnailLink":"https://encrypted-tbn0.gstatic.com/images?q=tbn:ANd9GcQdw0E9WNNFhqWAdEzkdXZ2Ps3dJLDnXPEmKfRaws2_Y-JoOp7vsIAWGB4&s",
        "thumbnailHeight":        135,
        "thumbnailWidth":        103      
      }    
    },
    {
      "kind":"customsearch#result",
      "title":"Ego Trippin' [PA] [LP] by Snoop Dogg (Vinyl, Mar-2008, Geffen ...",
      "htmlTitle":"<b>Ego Trippin</b>&#39; [PA] [LP] by <b>Snoop Dogg</b> (Vinyl, Mar-2008, Geffen ...",
      "link":"https://i.ebayimg.com/images/g/cn0AAOSw~e5ZUYFs/s-l640.jpg",
      "displayLink":"www.ebay.com",
      "snippet":"Ego Trippin' [PA] [LP] by Snoop Dogg (Vinyl, Mar-2008, Geffen ...",
      "htmlSnippet":"<b>Ego Trippin</b>&#39; [PA] [LP] by <b>Snoop Dogg</b> (Vinyl, Mar-2008, Geffen ...",
      "mime":"image/jpeg",
      "fileFormat":"image/jpeg",
      "image":      
      {
        "contextLink":"https://www.ebay.com/p/78453540",
        "height":        490,
        "width":        640,
        "byteSize":        50054,
        "thumbnailLink":"https://encrypted-tbn0.gstatic.com/images?q=tbn:ANd9GcRE1mBh6A3o3HO_BTX9-ekk4q6-de9Djs4xu7miUrTCQGYffBDDudEWYw&s",
        "thumbnailHeight":        105,
        "thumbnailWidth":        137      
      }    
    },
    {
      "kind":"customsearch#result",
      "title":"Snoop Dogg - Ego Trippin (2008, CD) | Discogs",
      "htmlTitle":"<b>Snoop Dogg</b> - <b>Ego Trippin</b> (2008, CD) | Discogs",
      "link":"https://img.discogs.com/6pAZKNxPq6ZBE0_P5c4fsLeyc8c=/fit-in/600x580/filters:strip_icc():format(jpeg):mode_rgb():quality(90)/discogs-images/R-1396331-1345869644-6505.jpeg.jpg",
      "displayLink":"www.discogs.com",
      "snippet":"Snoop Dogg - Ego Trippin (2008, CD) | Discogs",
      "htmlSnippet":"<b>Snoop Dogg</b> - <b>Ego Trippin</b> (2008, CD) | Discogs",
      "mime":"image/jpeg",
      "fileFormat":"image/jpeg",
      "image":      
      {
        "contextLink":"https://www.discogs.com/Snoop-Dogg-Ego-Trippin/release/1396331",
        "height":        580,
        "width":        600,
        "byteSize":        135220,
        "thumbnailLink":"https://encrypted-tbn0.gstatic.com/images?q=tbn:ANd9GcSy3dyqp4Hu4cYBa8cvQzqgXc3yGOI6KLQFUsCDZjy6RhcuYlm94HUKqGib&s",
        "thumbnailHeight":        131,
        "thumbnailWidth":        135      
      }    
    }  
  ]
}